{
	"lastUpdate": 1775023873615.717,
	"profiles": [
		{
			"id": 1751,
			"name": "Andripula",
			"ratings": {
				"naiveRating": 15.07
			},
			"classes": {
				"colour": "GOLD"
			},
			"mostRecentScoreTimeAchieved": 1743275752000,
			"totalScores": 330,
			"rankingData": {
				"naiveRating": {
					"ranking": 816,
					"outOf": 1566
				}
			},
			"playtime": 179971000
		},
		{
			"id": 1552,
			"name": "eclair",
			"ratings": {
				"naiveRating": 16.15
			},
			"classes": {
				"colour": "RAINBOW",
				"dan": "DAN_IV"
			},
			"mostRecentScoreTimeAchieved": 1760217885000,
			"totalScores": 3425,
			"rankingData": {
				"naiveRating": {
					"ranking": 401,
					"outOf": 1566
				}
			},
			"playtime": 1256993000
		},
		{
			"id": 2024,
			"name": "ItzFishy",
			"ratings": {
				"naiveRating": 17.27
			},
			"classes": {
				"colour": "RAINBOW_EX_II",
				"dan": "DAN_INFINITE",
				"emblem": "DAN_IV"
			},
			"mostRecentScoreTimeAchieved": 1775008008000,
			"totalScores": 5001,
			"rankingData": {
				"naiveRating": {
					"ranking": 58,
					"outOf": 1566
				}
			},
			"playtime": 1411116000
		},
		{
			"id": 1085,
			"name": "Litter",
			"ratings": {
				"naiveRating": 11.17
			},
			"classes": {
				"colour": "PURPLE"
			},
			"mostRecentScoreTimeAchieved": 1773284333000,
			"totalScores": 58,
			"rankingData": {
				"naiveRating": {
					"ranking": 1334,
					"outOf": 1566
				}
			},
			"playtime": 15768000
		},
		{
			"id": 1750,
			"name": "ryona",
			"ratings": {
				"naiveRating": 16.2
			},
			"classes": {
				"colour": "RAINBOW",
				"dan": "DAN_IV"
			},
			"mostRecentScoreTimeAchieved": 1775009045000,
			"totalScores": 1505,
			"rankingData": {
				"naiveRating": {
					"ranking": 375,
					"outOf": 1566
				}
			},
			"playtime": 437597000
		},
		{
			"id": 1703,
			"name": "Rythmik",
			"ratings": {
				"naiveRating": 17.46
			},
			"classes": {
				"dan": "DAN_INFINITE",
				"colour": "RAINBOW_EX_II"
			},
			"mostRecentScoreTimeAchieved": 1775006503000,
			"totalScores": 11585,
			"rankingData": {
				"naiveRating": {
					"ranking": 21,
					"outOf": 1566
				}
			},
			"playtime": 462092000
		},
		{
			"id": 397,
			"name": "The_Manwich",
			"ratings": {
				"naiveRating": 16.23
			},
			"classes": {
				"colour": "RAINBOW"
			},
			"mostRecentScoreTimeAchieved": 1754795406000,
			"totalScores": 1027,
			"rankingData": {
				"naiveRating": {
					"ranking": 364,
					"outOf": 1566
				}
			},
			"playtime": 481754381
		}
	]
}