{
	"lastUpdate": 1775066580937.4102,
	"profiles": [
		{
			"id": 1750,
			"name": "ryona",
			"ratings": {
				"BPI": null,
				"ktLampRating": 0
			},
			"classes": {},
			"mostRecentScoreTimeAchieved": 1754243444000,
			"totalScores": 1,
			"rankingData": {
				"ktLampRating": {
					"ranking": 993,
					"outOf": 1033
				},
				"BPI": {
					"ranking": 584,
					"outOf": 1033
				}
			},
			"playtime": 0
		},
		{
			"id": 1703,
			"name": "Rythmik",
			"ratings": {
				"BPI": null,
				"ktLampRating": 0.85
			},
			"classes": {},
			"mostRecentScoreTimeAchieved": 1734233220000,
			"totalScores": 9,
			"rankingData": {
				"ktLampRating": {
					"ranking": 961,
					"outOf": 1033
				},
				"BPI": {
					"ranking": 584,
					"outOf": 1033
				}
			},
			"playtime": 2040000
		},
		{
			"id": 397,
			"name": "The_Manwich",
			"ratings": {
				"ktLampRating": 12.359999999999998,
				"BPI": -8.540002937931671
			},
			"classes": {
				"dan": "DAN_10"
			},
			"mostRecentScoreTimeAchieved": 1768944812814,
			"totalScores": 3375,
			"rankingData": {
				"ktLampRating": {
					"ranking": 311,
					"outOf": 1033
				},
				"BPI": {
					"ranking": 317,
					"outOf": 1033
				}
			},
			"playtime": 965048813
		}
	]
}