{
	"lastUpdate": 1782324087318.5579,
	"profiles": [
		{
			"id": 1750,
			"name": "ryona",
			"ratings": {
				"BPI": null,
				"ktLampRating": 0,
				"ktLampRatingHC": 0,
				"ktLampRatingEXHC": 0
			},
			"classes": {},
			"mostRecentScoreTimeAchieved": 1754243444000,
			"totalScores": 1,
			"rankingData": {
				"ktLampRating": {
					"ranking": 1049,
					"outOf": 1091
				},
				"ktLampRatingHC": {
					"ranking": 930,
					"outOf": 1091
				},
				"ktLampRatingEXHC": {
					"ranking": 892,
					"outOf": 1091
				},
				"BPI": {
					"ranking": 1091,
					"outOf": 1091
				}
			},
			"playtime": 0
		},
		{
			"id": 1703,
			"name": "Rythmik",
			"ratings": {
				"BPI": null,
				"ktLampRating": 0.85,
				"ktLampRatingHC": 0.15,
				"ktLampRatingEXHC": 0
			},
			"classes": {},
			"mostRecentScoreTimeAchieved": 1734233220000,
			"totalScores": 9,
			"rankingData": {
				"ktLampRating": {
					"ranking": 1011,
					"outOf": 1091
				},
				"ktLampRatingHC": {
					"ranking": 912,
					"outOf": 1091
				},
				"ktLampRatingEXHC": {
					"ranking": 892,
					"outOf": 1091
				},
				"BPI": {
					"ranking": 1091,
					"outOf": 1091
				}
			},
			"playtime": 2040000
		},
		{
			"id": 397,
			"name": "The_Manwich",
			"ratings": {
				"BPI": -8.540002937931671,
				"ktLampRating": 12.359999999999998,
				"ktLampRatingHC": 11.829999999999998,
				"ktLampRatingEXHC": 10.35
			},
			"classes": {
				"dan": "DAN_10"
			},
			"mostRecentScoreTimeAchieved": 1768944812814,
			"totalScores": 3375,
			"rankingData": {
				"ktLampRating": {
					"ranking": 324,
					"outOf": 1091
				},
				"ktLampRatingHC": {
					"ranking": 342,
					"outOf": 1091
				},
				"ktLampRatingEXHC": {
					"ranking": 304,
					"outOf": 1091
				},
				"BPI": {
					"ranking": 327,
					"outOf": 1091
				}
			},
			"playtime": 965048813
		}
	]
}